getadvice/__init__.py
getadvice/getadvice.py
getadvice-0.1.6.dist-info/WHEEL
getadvice-0.1.6.dist-info/METADATA
getadvice-0.1.6.dist-info/RECORD
