Metadata-Version: 2.1
Name: getadvice
Version: 0.1.6
Summary: This is a fancy `Hello World` to publishing Python library to PyPi.
License: MIT
Author: Rich Leung
Author-email: kleung.hkg@gmail.com
Requires-Python: >=3.0,<4.0
Classifier: License :: OSI Approved :: MIT License
Classifier: Programming Language :: Python :: 3
Classifier: Programming Language :: Python :: 3.4
Classifier: Programming Language :: Python :: 3.5
Classifier: Programming Language :: Python :: 3.6
Classifier: Programming Language :: Python :: 3.7
Classifier: Programming Language :: Python :: 3.8
Classifier: Programming Language :: Python :: 3.9
Requires-Dist: requests (>=2.24.0,<3.0.0)
